basemodels/__init__.py
basemodels/constants.py
basemodels/helpers.py
basemodels/via.py
basemodels/manifest/__init__.py
basemodels/manifest/manifest.py
basemodels/manifest/restricted_audience.py
basemodels/manifest/data/__init__.py
basemodels/manifest/data/groundtruth.py
basemodels/manifest/data/helpers.py
basemodels/manifest/data/preprocess.py
basemodels/manifest/data/requester_question_example.py
basemodels/manifest/data/requester_restricted_answer_set.py
basemodels/manifest/data/taskdata.py
hmt_basemodels-1.3.0.dist-info/LICENSE
hmt_basemodels-1.3.0.dist-info/METADATA
hmt_basemodels-1.3.0.dist-info/WHEEL
hmt_basemodels-1.3.0.dist-info/top_level.txt
hmt_basemodels-1.3.0.dist-info/zip-safe
hmt_basemodels-1.3.0.dist-info/RECORD
