Metadata-Version: 2.1
Name: hmt-basemodels
Version: 1.3.0
Summary: Common data models shared by various components of the Human Protocol stack
Home-page: https://github.com/hCaptcha/hmt-basemodels
Author: HUMAN Protocol
Classifier: Intended Audience :: Developers
Classifier: Operating System :: OS Independent
Classifier: Programming Language :: Python
License-File: LICENSE
Requires-Dist: requests >=2
Requires-Dist: typing-extensions
Requires-Dist: pydantic >=2.5.3
